{
  "name": "USAF 33rd Wing Mustangs F-35B 1-17",
  "aircrafts": {
    "5229": {
      "name": "F-35B Lightning II (by JAaMDG)",
      "liveries": [
        {
          "name": "01",
          "texture": [
            "https://i.ibb.co/p6RCLrwp/1.png"
          ],
          "thumbnail": "https://i.ibb.co/HpRC19X4/Screenshot-2025-04-07-225722.png"
        },
        {
          "name": "02",
          "texture": [
            "https://i.ibb.co/y2Rzc05/2.png"
          ],
          "thumbnail": "https://i.ibb.co/HpRC19X4/Screenshot-2025-04-07-225722.png"
        },
        {
          "name": "03",
          "texture": [
            "https://i.ibb.co/RGPRPT3f/3.png"
          ],
          "thumbnail": "https://i.ibb.co/HpRC19X4/Screenshot-2025-04-07-225722.png"
        },
        {
          "name": "04",
          "texture": [
            "https://i.ibb.co/LDHj7b9b/4.png"
          ],
          "thumbnail": "https://i.ibb.co/HpRC19X4/Screenshot-2025-04-07-225722.png"
        },
        {
          "name": "05",
          "texture": [
            "https://i.ibb.co/FLpwKyz9/5.png"
          ],
          "thumbnail": "https://i.ibb.co/HpRC19X4/Screenshot-2025-04-07-225722.png"
        },
        {
          "name": "06",
          "texture": [
            "https://i.ibb.co/whMWvjNk/6.png"
          ],
          "thumbnail": "https://i.ibb.co/HpRC19X4/Screenshot-2025-04-07-225722.png"
        },
        {
          "name": "07",
          "texture": [
            "https://i.ibb.co/Csbfvr1m/7.png"
          ],
          "thumbnail": "https://i.ibb.co/HpRC19X4/Screenshot-2025-04-07-225722.png"
        },
        {
          "name": "08",
          "texture": [
            "https://i.ibb.co/4ZFhTBVm/8.png"
          ],
          "thumbnail": "https://i.ibb.co/HpRC19X4/Screenshot-2025-04-07-225722.png"
        },
        {
          "name": "09",
          "texture": [
            "https://i.ibb.co/9mSFvmGH/9.png"
          ],
          "thumbnail": "https://i.ibb.co/HpRC19X4/Screenshot-2025-04-07-225722.png"
        },
        {
          "name": "10",
          "texture": [
            "https://i.ibb.co/dszfTy1F/10.png"
          ],
          "thumbnail": "https://i.ibb.co/HpRC19X4/Screenshot-2025-04-07-225722.png"
        },
        {
          "name": "11",
          "texture": [
            "https://i.ibb.co/N25xQBxm/11.png"
          ],
          "thumbnail": "https://i.ibb.co/HpRC19X4/Screenshot-2025-04-07-225722.png"
        },
        {
          "name": "12",
          "texture": [
            "https://i.ibb.co/1tVpjzyW/12.png"
          ],
          "thumbnail": "https://i.ibb.co/HpRC19X4/Screenshot-2025-04-07-225722.png"
        },
        {
          "name": "13",
          "texture": [
            "https://i.ibb.co/B1HyJWC/13.png"
          ],
          "thumbnail": "https://i.ibb.co/HpRC19X4/Screenshot-2025-04-07-225722.png"
        },
        {
          "name": "14",
          "texture": [
            "https://i.ibb.co/whbvwW6M/14.png"
          ],
          "thumbnail": "https://i.ibb.co/HpRC19X4/Screenshot-2025-04-07-225722.png"
        },
        {
          "name": "15",
          "texture": [
            "https://i.ibb.co/vxr3cytc/15.png"
          ],
          "thumbnail": "https://i.ibb.co/HpRC19X4/Screenshot-2025-04-07-225722.png"
        },
        {
          "name": "16",
          "texture": [
            "https://i.ibb.co/k6ShcT7R/16.png"
          ],
          "thumbnail": "https://i.ibb.co/HpRC19X4/Screenshot-2025-04-07-225722.png"
        },
        {
          "name": "17",
          "texture": [
            "https://i.ibb.co/GQrS3Gp3/17.png"
          ],
          "thumbnail": "https://i.ibb.co/HpRC19X4/Screenshot-2025-04-07-225722.png"
        }
      ]
    }
  }
}
